aws_cost_optimization_8/__init__.py
aws_cost_optimization_8/_cloudwatch_costing.py
aws_cost_optimization_8/_ec2_costing.py
aws_cost_optimization_8/_kms_costing.py
aws_cost_optimization_8/_rds_costing.py
aws_cost_optimization_8/_ri_recommendations.py
aws_cost_optimization_8/_savings_plan.py
aws_cost_optimization_8/utils.py
aws_cost_optimization_8-0.2.7.dist-info/LICENCE
aws_cost_optimization_8-0.2.7.dist-info/METADATA
aws_cost_optimization_8-0.2.7.dist-info/WHEEL
aws_cost_optimization_8-0.2.7.dist-info/top_level.txt
aws_cost_optimization_8-0.2.7.dist-info/RECORD
